registration_asistant_ner/training_data/pdf_reader.py
project_koha_dspace_ner-0.1.0.dist-info/METADATA
project_koha_dspace_ner-0.1.0.dist-info/WHEEL
project_koha_dspace_ner-0.1.0.dist-info/RECORD
