Metadata-Version: 2.4
Name: project-koha-dspace-ner
Version: 0.1.0
Summary: A project to extract named entities from UMSA's academic repository documents
Author: Rodrigo Iturralde
License-Expression: MIT
Keywords: dspace,koha,ner,nlp,umsa
Requires-Python: >=3.12
Requires-Dist: numpy~=2.2.1
Requires-Dist: opencv-python-headless~=4.10.0.84
Requires-Dist: pymupdf~=1.24.14
Requires-Dist: pytesseract==0.3.13
